tikzpics/__init__.py
tikzpics/base.py
tikzpics/color.py
tikzpics/coordinate.py
tikzpics/figure.py
tikzpics/layer.py
tikzpics/linestyle.py
tikzpics/loop.py
tikzpics/node.py
tikzpics/path.py
tikzpics/plot.py
tikzpics/variable.py
tikzpics/wrapper.py
tikzpics/console/__init__.py
tikzpics/console/main.py
tikzpics/tests/unit/__init__.py
tikzpics/tests/unit/test_app.py
tikzpics/tests/unit/test_layer.py
tikzpics/tests/unit/test_tikz_generation.py
tikzpics-0.1.1.dist-info/METADATA
tikzpics-0.1.1.dist-info/WHEEL
tikzpics-0.1.1.dist-info/top_level.txt
tikzpics-0.1.1.dist-info/RECORD
