Metadata-Version: 2.4
Name: tikzpics
Version: 0.1.1
Summary: Python interface to generate (readable) Tikz figures.
Author: Max
Project-URL: Source, https://github.com/max-models/tikzpics
Keywords: python
Classifier: Development Status :: 3 - Alpha
Requires-Python: >=3.8
Requires-Dist: pymupdf
Provides-Extra: test
Requires-Dist: pytest; extra == "test"
Requires-Dist: coverage; extra == "test"
Provides-Extra: dev
Requires-Dist: tikzpics[test]; extra == "dev"
Requires-Dist: black[jupyter]; extra == "dev"
Requires-Dist: isort; extra == "dev"
Requires-Dist: ruff; extra == "dev"
Requires-Dist: pre-commit; extra == "dev"
Requires-Dist: pyproject-fmt; extra == "dev"
Requires-Dist: jupyterlab; extra == "dev"
Requires-Dist: ipykernel; extra == "dev"
Requires-Dist: numpy; extra == "dev"
Requires-Dist: scipy; extra == "dev"
Provides-Extra: docs
Requires-Dist: myst-parser; extra == "docs"
Requires-Dist: nbconvert; extra == "docs"
Requires-Dist: nbsphinx; extra == "docs"
Requires-Dist: sphinx; extra == "docs"
Requires-Dist: sphinx_bootstrap_theme; extra == "docs"
